ptop/__init__.py
ptop/constants.py
ptop/main.py
ptop/core/__init__.py
ptop/core/plugin.py
ptop/interfaces/GUI.py
ptop/interfaces/__init__.py
ptop/plugins/__init__.py
ptop/plugins/cpu_sensor.py
ptop/plugins/disk_sensor.py
ptop/plugins/memory_sensor.py
ptop/plugins/network_sensor.py
ptop/plugins/process_sensor.py
ptop/plugins/system_sensor.py
ptop/statistics/__init__.py
ptop/statistics/statistics.py
ptop/utils/__init__.py
ptop/utils/thread_jobs.py
ptop-1.0.data/data/CONTRIBUTORS.md
ptop-1.0.data/data/LICENSE
ptop-1.0.data/data/README.md
ptop-1.0.data/data/VERSION
ptop-1.0.dist-info/LICENSE
ptop-1.0.dist-info/METADATA
ptop-1.0.dist-info/WHEEL
ptop-1.0.dist-info/entry_points.txt
ptop-1.0.dist-info/top_level.txt
ptop-1.0.dist-info/RECORD
