Metadata-Version: 2.1
Name: ptop
Version: 1.0
Summary: A task manager written in Python
Home-page: https://github.com/darxtrix/ptop
Author: Ankush Sharma
Author-email: darxtrix@gmail.com
License: MIT
Download-URL: https://github.com/darxtrix/ptop/releases/download/v1.0/ptop-1.0.tar.gz
Keywords: top ptop task manager python
Platform: UNKNOWN
Classifier: Development Status :: 5 - Production/Stable
Classifier: Intended Audience :: Information Technology
Classifier: Natural Language :: English
Classifier: Topic :: System :: Monitoring
Classifier: License :: OSI Approved :: MIT License
Classifier: Programming Language :: Python :: 2
Classifier: Programming Language :: Python :: 2.7
Classifier: Programming Language :: Python :: 3
Classifier: Programming Language :: Python :: 3.3
Classifier: Programming Language :: Python :: 3.4
Classifier: Programming Language :: Python :: 3.5
Classifier: Programming Language :: Python :: 3.6
Classifier: Programming Language :: Python :: 3.7
Requires-Dist: npyscreen (>=4.10.5)
Requires-Dist: psutil (>=3.0.1)
Requires-Dist: argparse (>=1.2.1)
Requires-Dist: certifi (>=2018.10.15)
Requires-Dist: chardet (>=3.0.4)
Requires-Dist: drawille (>=0.1.0)
Requires-Dist: requests (>=2.20.1)
Requires-Dist: urllib3 (>=1.24.1)
Requires-Dist: huepy (>=0.9.8.1)
